adroit/Adroit.py
adroit/Adroit.pyi
adroit/__init__.py
adroit_py-0.1.1.dist-info/licenses/LICENSE
adroit_py-0.1.1.dist-info/METADATA
adroit_py-0.1.1.dist-info/WHEEL
adroit_py-0.1.1.dist-info/top_level.txt
adroit_py-0.1.1.dist-info/RECORD
