Metadata-Version: 2.4
Name: adroit-py
Version: 0.1.1
Summary: Lightweight Python wrapper for Adroit OLE server runtime
Author: Diego Acuña
Author-email: Diego Acuña <diegoa@adroit.co.za>
License: MIT
Project-URL: Homepage, https://github.com/yourrepo
Requires-Python: >=3.10
License-File: LICENSE
Requires-Dist: pywin32>=305; sys_platform == "win32"
Dynamic: license-file
